<archimate:ArchimateDiagramModel
    xmlns:xsi="http://www.w3.org/2001/XMLSchema-instance"
    xmlns:archimate="http://www.archimatetool.com/archimate"
    name="М8 Матрица ОГР модуль ВВ2"
    id="6fb9bc3d-c770-4447-a896-78c2061ce891">
  <children
      xsi:type="archimate:DiagramModelArchimateObject"
      id="d51e35b5-824d-4c23-a84e-13a3788a296c">
    <bounds
        x="185"
        y="240"
        width="120"
        height="55"/>
    <archimateElement
        xsi:type="archimate:Constraint"
        href="Constraint_de789377-eea8-44b2-a3be-5381dbcc87bc.xml#de789377-eea8-44b2-a3be-5381dbcc87bc"/>
  </children>
  <children
      xsi:type="archimate:DiagramModelArchimateObject"
      id="08e14560-0aa1-43eb-b8cb-3360d425dfb7">
    <bounds
        x="185"
        y="294"
        width="120"
        height="55"/>
    <archimateElement
        xsi:type="archimate:Constraint"
        href="Constraint_34d88093-8818-47c2-ae9a-4aff2c6da9fb.xml#34d88093-8818-47c2-ae9a-4aff2c6da9fb"/>
  </children>
  <children
      xsi:type="archimate:DiagramModelArchimateObject"
      id="14cbb132-ef8f-43f9-a848-db1d6de7a44e">
    <bounds
        x="185"
        y="348"
        width="120"
        height="55"/>
    <archimateElement
        xsi:type="archimate:Constraint"
        href="Constraint_cb34623c-375e-487e-abe4-4b633a791fd4.xml#cb34623c-375e-487e-abe4-4b633a791fd4"/>
  </children>
  <children
      xsi:type="archimate:DiagramModelArchimateObject"
      id="f2662841-916a-4c38-8f13-cb798aee9a9e">
    <bounds
        x="192"
        y="402"
        width="120"
        height="55"/>
    <archimateElement
        xsi:type="archimate:Constraint"
        href="Constraint_198dbd47-5c59-43f7-83ce-1e765d37143a.xml#198dbd47-5c59-43f7-83ce-1e765d37143a"/>
  </children>
  <children
      xsi:type="archimate:DiagramModelArchimateObject"
      id="f45c8fae-0788-4373-8d4b-0db4ebfb5720">
    <bounds
        x="412"
        y="90"
        width="120"
        height="55"/>
    <archimateElement
        xsi:type="archimate:Node"
        href="Node_949c97a6-4092-475b-877e-d9f894a0e3d1.xml#949c97a6-4092-475b-877e-d9f894a0e3d1"/>
  </children>
  <children
      xsi:type="archimate:DiagramModelArchimateObject"
      id="e5bdd1d3-b67d-4722-93ad-8bb3fceb4c10">
    <bounds
        x="639"
        y="131"
        width="120"
        height="55"/>
    <archimateElement
        xsi:type="archimate:Node"
        href="Node_621d01d2-7bcd-4da6-b6e2-6b4b7265cb90.xml#621d01d2-7bcd-4da6-b6e2-6b4b7265cb90"/>
  </children>
  <children
      xsi:type="archimate:DiagramModelArchimateObject"
      id="3934e449-83a1-43ca-bc06-97ee9d7c6352">
    <bounds
        x="789"
        y="131"
        width="120"
        height="55"/>
    <archimateElement
        xsi:type="archimate:Node"
        href="Node_1bafb9a0-45cb-464c-8e89-3c2cd3076e89.xml#1bafb9a0-45cb-464c-8e89-3c2cd3076e89"/>
  </children>
  <children
      xsi:type="archimate:DiagramModelArchimateObject"
      id="16ce0e32-caff-4f92-9126-fc1b773e8fc6">
    <bounds
        x="939"
        y="131"
        width="120"
        height="55"/>
    <archimateElement
        xsi:type="archimate:Node"
        href="Node_4d372515-af82-4ba8-9f6e-d78b902d874b.xml#4d372515-af82-4ba8-9f6e-d78b902d874b"/>
  </children>
  <children
      xsi:type="archimate:DiagramModelArchimateObject"
      id="e23fafd6-964f-4db0-8b9c-a08fd9ec1976">
    <bounds
        x="639"
        y="231"
        width="120"
        height="55"/>
    <archimateElement
        xsi:type="archimate:Node"
        href="Node_5632813a-4bf2-4c34-be18-9e852a771a6a.xml#5632813a-4bf2-4c34-be18-9e852a771a6a"/>
  </children>
  <children
      xsi:type="archimate:DiagramModelArchimateObject"
      id="bd135164-d4ce-40c3-b8a4-a8eeea4ed390">
    <bounds
        x="789"
        y="231"
        width="120"
        height="55"/>
    <archimateElement
        xsi:type="archimate:Node"
        href="Node_2143be44-62a9-4022-a076-349f7af70d52.xml#2143be44-62a9-4022-a076-349f7af70d52"/>
  </children>
  <children
      xsi:type="archimate:DiagramModelArchimateObject"
      id="907a62ce-51e7-480a-825f-9715c0848afa">
    <bounds
        x="639"
        y="331"
        width="120"
        height="55"/>
    <archimateElement
        xsi:type="archimate:Node"
        href="Node_87a21600-0168-448f-8772-ddb1a6a22c09.xml#87a21600-0168-448f-8772-ddb1a6a22c09"/>
  </children>
  <children
      xsi:type="archimate:DiagramModelArchimateObject"
      id="42840799-3c9a-4013-8cf2-3269b6767e93">
    <bounds
        x="939"
        y="331"
        width="120"
        height="55"/>
    <archimateElement
        xsi:type="archimate:Node"
        href="Node_e2dd7422-1b56-4d4e-b7e9-fd41e2bbc99f.xml#e2dd7422-1b56-4d4e-b7e9-fd41e2bbc99f"/>
  </children>
  <children
      xsi:type="archimate:DiagramModelArchimateObject"
      id="adadf626-8b4e-4a68-8053-3a8db5d38598">
    <bounds
        x="789"
        y="431"
        width="120"
        height="55"/>
    <archimateElement
        xsi:type="archimate:Node"
        href="Node_a2d03514-3917-46f3-ba36-ed7d0ba01745.xml#a2d03514-3917-46f3-ba36-ed7d0ba01745"/>
  </children>
  <children
      xsi:type="archimate:DiagramModelArchimateObject"
      id="f0ba80cc-4472-4c19-b412-aef06971edef">
    <bounds
        x="804"
        y="331"
        width="120"
        height="55"/>
    <archimateElement
        xsi:type="archimate:Node"
        href="Node_f397e034-07b4-4796-b9b9-cec4155cbf18.xml#f397e034-07b4-4796-b9b9-cec4155cbf18"/>
  </children>
  <children
      xsi:type="archimate:DiagramModelArchimateObject"
      id="cf7ab88e-1956-48f6-858d-6932e3a05dae">
    <bounds
        x="948"
        y="231"
        width="120"
        height="55"/>
    <archimateElement
        xsi:type="archimate:Node"
        href="Node_26890bef-dccf-4f02-8129-e53073d9af6b.xml#26890bef-dccf-4f02-8129-e53073d9af6b"/>
  </children>
</archimate:ArchimateDiagramModel>
